<!DOCTYPE QGLVIEWER>
<QGLViewer version="2.5.0">
  <State stereo="false" cameraMode="revolve">
    <foregroundColor red="180" blue="180" green="180"/>
    <backgroundColor red="51" blue="51" green="51"/>
  </State>
  <Display axisIsDrawn="false" gridIsDrawn="false" FPSIsDisplayed="false" cameraIsEdited="false"/>
  <Geometry fullScreen="false" width="1920" posX="1920" height="1053" posY="0"/>
  <Camera>
    <Parameters fieldOfView="0.785398" sceneRadius="1" Type="PERSPECTIVE" zNearCoefficient="0.005" orthoCoef="0.414214" zClippingCoefficient="1.73205">
      <SceneCenter x="0" y="0" z="0"/>
    </Parameters>
    <Stereo focusDistance="2.41421" physScreenWidth="0.5" IODist="0.062"/>
    <ManipulatedCameraFrame>
      <position x="0.428389" y="-1.86619" z="-2.2395"/>
      <orientation q0="0.923984" q1="0.201823" q2="-0.130374" q3="0.297529"/>
      <ManipulatedParameters transSens="1" rotSens="1" wheelSens="1" spinSens="0.3"/>
      <ManipulatedCameraParameters flySpeed="0.01">
        <flyUpVector x="0" y="1" z="0"/>
      </ManipulatedCameraParameters>
    </ManipulatedCameraFrame>
  </Camera>
</QGLViewer>
